celestine/__init__.py
celestine/__main__.py
celestine/bank.py
celestine/literal.py
celestine/load.py
celestine/py.typed
celestine/regex.py
celestine/stream.py
celestine/typed.py
celestine/typed_test.py
celestine/application/__init__.py
celestine/application/demo.py
celestine/application/photo.py
celestine/application/test.py
celestine/application/clean/__init__.py
celestine/application/clean/code.py
celestine/application/clean/data.py
celestine/application/clean/unicode_tool.py
celestine/application/clean/verify.py
celestine/application/clean/view.py
celestine/application/logo/__init__.py
celestine/application/logo/code.py
celestine/application/logo/view.py
celestine/application/translator/__init__.py
celestine/application/translator/code.py
celestine/application/translator/data.py
celestine/application/translator/main.py
celestine/application/translator/read.py
celestine/application/translator/translator.py
celestine/application/translator/view.py
celestine/application/translator/write.py
celestine/application/viewer/__init__.py
celestine/application/viewer/code.py
celestine/application/viewer/data.py
celestine/application/viewer/view.py
celestine/data/__init__.py
celestine/data/alphabet.py
celestine/data/alphabet2.py
celestine/data/cascadia_code_regular.otf
celestine/data/directory.py
celestine/data/icon.png
celestine/data/main.py
celestine/data/normalize.py
celestine/data/notational_systems.py
celestine/data/palette.py
celestine/interface/__init__.py
celestine/interface/blender.py
celestine/interface/curses.py
celestine/interface/dearpygui.py
celestine/interface/pygame.py
celestine/interface/tkinter.py
celestine/language/__init__.py
celestine/language/bg.py
celestine/language/cs.py
celestine/language/da.py
celestine/language/de.py
celestine/language/el.py
celestine/language/en.py
celestine/language/es.py
celestine/language/et.py
celestine/language/fi.py
celestine/language/fr.py
celestine/language/ga.py
celestine/language/hr.py
celestine/language/hu.py
celestine-2025.2.17.dist-info/LICENCE.txt
celestine-2025.2.17.dist-info/METADATA
celestine-2025.2.17.dist-info/WHEEL
celestine-2025.2.17.dist-info/top_level.txt
celestine-2025.2.17.dist-info/RECORD
