Metadata-Version: 2.2
Name: celestine
Version: 2025.2.17
Summary: A python framework for desktop applications.
Author-email: Marian Molyneux <celestine@cyanochroite.com>
Maintainer-email: mem_dixy <mem_dixy@pm.me>
Project-URL: Documentation, https://celestine.readthedocs.io/
Project-URL: Source, https://github.com/cyanochroite/celestine
Project-URL: Tracker, https://github.com/cyanochroite/celestine/issues
Project-URL: Discord, https://discord.gg/aNmDWPXd7B
Keywords: python,application,wrapper,framework,localization,cross-platform,offline,desktop,celestine,image-viewer
Classifier: Development Status :: 3 - Alpha
Classifier: Intended Audience :: Developers
Classifier: License :: OSI Approved :: European Union Public Licence 1.2 (EUPL 1.2)
Classifier: Natural Language :: Bulgarian
Classifier: Natural Language :: Croatian
Classifier: Natural Language :: Czech
Classifier: Natural Language :: Danish
Classifier: Natural Language :: Dutch
Classifier: Natural Language :: English
Classifier: Natural Language :: Finnish
Classifier: Natural Language :: French
Classifier: Natural Language :: German
Classifier: Natural Language :: Greek
Classifier: Natural Language :: Hungarian
Classifier: Natural Language :: Irish
Classifier: Natural Language :: Italian
Classifier: Natural Language :: Latvian
Classifier: Natural Language :: Lithuanian
Classifier: Natural Language :: Polish
Classifier: Natural Language :: Portuguese
Classifier: Natural Language :: Romanian
Classifier: Natural Language :: Slovak
Classifier: Natural Language :: Slovenian
Classifier: Natural Language :: Spanish
Classifier: Natural Language :: Swedish
Classifier: Operating System :: OS Independent
Classifier: Programming Language :: Python :: 3.12
Classifier: Topic :: Software Development :: Libraries :: Application Frameworks
Classifier: Topic :: Software Development :: User Interfaces
Classifier: Typing :: Typed
Requires-Python: >=3.12
License-File: LICENCE.txt
Requires-Dist: Pillow>=10.0.0
Requires-Dist: platformdirs>=4.0.0
Provides-Extra: build
Requires-Dist: blender-stubs; extra == "build"
Requires-Dist: build; extra == "build"
Requires-Dist: coverage; extra == "build"
Requires-Dist: flake8; extra == "build"
Requires-Dist: mypy; extra == "build"
Requires-Dist: pip; extra == "build"
Requires-Dist: pycodestyle; extra == "build"
Requires-Dist: pylint; extra == "build"
Requires-Dist: pyright; extra == "build"
Requires-Dist: pytest; extra == "build"
Requires-Dist: ruff; extra == "build"
Requires-Dist: Sphinx; extra == "build"
Requires-Dist: twine; extra == "build"
Requires-Dist: types-requests; extra == "build"
Provides-Extra: clean
Requires-Dist: autoflake; extra == "clean"
Requires-Dist: black; extra == "clean"
Requires-Dist: isort; extra == "clean"
Requires-Dist: pydocstringformatter; extra == "clean"
Requires-Dist: pyupgrade; extra == "clean"
Provides-Extra: demo
Requires-Dist: requests; extra == "demo"
Provides-Extra: gui
Requires-Dist: dearpygui; extra == "gui"
Requires-Dist: pygame; extra == "gui"
Requires-Dist: windows-curses; platform_system == "Windows" and extra == "gui"
